icopy2xls/FilesOpen.py
icopy2xls/__init__.py
icopy2xls-0.0.4.dist-info/LICENSE
icopy2xls-0.0.4.dist-info/METADATA
icopy2xls-0.0.4.dist-info/WHEEL
icopy2xls-0.0.4.dist-info/top_level.txt
icopy2xls-0.0.4.dist-info/RECORD
