Metadata-Version: 2.1
Name: icopy2xls
Version: 0.0.4
Summary: Append rows of one Excel sheet to another, if header lines fit
Home-page: https://baangt.org
Author: Bernhard Buhl
Author-email: info@baangt.org
License: UNKNOWN
Platform: UNKNOWN
Classifier: Programming Language :: Python :: 3
Classifier: License :: OSI Approved :: MIT License
Classifier: Operating System :: OS Independent
Requires-Python: >=3.6
Requires-Dist: xlrd3
Requires-Dist: openpyxl
